pytree2safetensors/__init__.py
pytree2safetensors/_shared_types.py
pytree2safetensors/load.py
pytree2safetensors/save.py
pytree2safetensors/serialise.py
pytree2safetensors-0.1.4.dist-info/METADATA
pytree2safetensors-0.1.4.dist-info/WHEEL
pytree2safetensors-0.1.4.dist-info/licenses/LICENSE
pytree2safetensors-0.1.4.dist-info/RECORD
