Metadata-Version: 2.3
Name: pytree2safetensors
Version: 0.1.4
Summary: A simple package to save and load JAX PyTrees to and from Safetensors
Project-URL: Homepage, https://github.com/cooljoseph1/pytree2safetensors
Project-URL: Issues, https://github.com/cooljoseph1/pytree2safetensors/issues
Author-email: Joseph Camacho <camacho.joseph@gmail.com>
License-File: LICENSE
Classifier: License :: OSI Approved :: MIT License
Classifier: Operating System :: OS Independent
Classifier: Programming Language :: Python :: 3
Requires-Python: >=3.10
Requires-Dist: jax
Requires-Dist: jaxtyping
Requires-Dist: safetensors
